MANIFEST.in
setup.py
routing/__init__.py
routing/multipart.py
routing.egg-info/PKG-INFO
routing.egg-info/SOURCES.txt
routing.egg-info/dependency_links.txt
routing.egg-info/top_level.txt