Metadata-Version: 1.1
Name: routing
Version: 0.2.0
Summary: request routing, that's it
Home-page: http://github.com/teepark/shorty
Author: Travis Parker
Author-email: travis.parker@gmail.com
License: BSD
Platform: UNKNOWN
Classifier: Development Status :: 4 - Beta
Classifier: Intended Audience :: Developers
Classifier: License :: OSI Approved :: BSD License
Classifier: Natural Language :: English
Classifier: Programming Language :: Python
